{
  "code":0,
  "count":26,
  "data":[
    {
      "id":1,
      "name":"测试mysql",
      "data_con":"测试文件内容",
      "lrsj":"2019-11-21",
      "xgsj":"2019-11-21"
    },{
      "id":2,
      "name":"测试mysql1",
      "data_con":"测试文件内容1",
      "lrsj":"2019-11-21",
      "xgsj":"2019-11-21"
    },{
      "id":3,
      "name":"测试mysql3",
      "data_con":"测试文件内容3",
      "lrsj":"2019-11-21",
      "xgsj":"2019-11-21"
    },{
      "id":4,
      "name":"测试mysql4",
      "data_con":"测试文件内容4",
      "lrsj":"2019-11-21",
      "xgsj":"2019-11-21"
    },{
      "id":5,
      "name":"测试mysql5",
      "data_con":"测试文件内容5",
      "lrsj":"2019-11-21",
      "xgsj":"2019-11-21"
    },{
      "id":6,
      "name":"测试mysql6",
      "data_con":"测试文件内容6",
      "lrsj":"2019-11-21",
      "xgsj":"2019-11-21"
    },{
      "id":7,
      "name":"测试mysql7",
      "data_con":"测试文件内容7",
      "lrsj":"2019-11-21",
      "xgsj":"2019-11-21"
    },{
      "id":8,
      "name":"测试mysql8",
      "data_con":"测试文件内容8",
      "lrsj":"2019-11-21",
      "xgsj":"2019-11-21"
    },{
      "id":9,
      "name":"测试mysql9",
      "data_con":"测试文件内容9",
      "lrsj":"2019-11-21",
      "xgsj":"2019-11-21"
    },{
      "id":10,
      "name":"测试mysql10",
      "data_con":"测试文件内容10",
      "lrsj":"2019-11-21",
      "xgsj":"2019-11-21"
    },{
      "id":11,
      "name":"测试mysql11",
      "data_con":"测试文件内容11",
      "lrsj":"2019-11-21",
      "xgsj":"2019-11-21"
    },{
      "id":12,
      "name":"测试mysql12",
      "data_con":"测试文件内容12",
      "lrsj":"2019-11-21",
      "xgsj":"2019-11-21"
    },{
      "id":13,
      "name":"测试mysql13",
      "data_con":"测试文件内容13",
      "lrsj":"2019-11-21",
      "xgsj":"2019-11-21"
    },{
      "id":14,
      "name":"测试mysql14",
      "data_con":"测试文件内容14",
      "lrsj":"2019-11-21",
      "xgsj":"2019-11-21"
    },{
      "id":15,
      "name":"测试mysql15",
      "data_con":"测试文件内容15",
      "lrsj":"2019-11-21",
      "xgsj":"2019-11-21"
    },{
      "id":16,
      "name":"测试mysql16",
      "data_con":"测试文件内容16",
      "lrsj":"2019-11-21",
      "xgsj":"2019-11-21"
    },{
      "id":17,
      "name":"测试mysql17",
      "data_con":"测试文件内容17",
      "lrsj":"2019-11-21",
      "xgsj":"2019-11-21"
    },{
      "id":18,
      "name":"测试mysql18",
      "data_con":"测试文件内容18",
      "lrsj":"2019-11-21",
      "xgsj":"2019-11-21"
    },{
      "id":19,
      "name":"测试mysql19",
      "data_con":"测试文件内容19",
      "lrsj":"2019-11-21",
      "xgsj":"2019-11-21"
    },{
      "id":20,
      "name":"测试mysql20",
      "data_con":"测试文件内容20",
      "lrsj":"2019-11-21",
      "xgsj":"2019-11-21"
    },{
      "id":21,
      "name":"测试mysql21",
      "data_con":"测试文件内容21",
      "lrsj":"2019-11-21",
      "xgsj":"2019-11-21"
    },{
      "id":22,
      "name":"测试mysql22",
      "data_con":"测试文件内容22",
      "lrsj":"2019-11-21",
      "xgsj":"2019-11-21"
    },{
      "id":23,
      "name":"测试mysql23",
      "data_con":"测试文件内容23",
      "lrsj":"2019-11-21",
      "xgsj":"2019-11-21"
    },{
      "id":24,
      "name":"测试mysql24",
      "data_con":"测试文件内容24",
      "lrsj":"2019-11-21",
      "xgsj":"2019-11-21"
    },{
      "id":25,
      "name":"测试mysql25",
      "data_con":"测试文件内容25",
      "lrsj":"2019-11-21",
      "xgsj":"2019-11-21"
    },{
      "id":26,
      "name":"测试mysql26",
      "data_con":"测试文件内容26",
      "lrsj":"2019-11-21",
      "xgsj":"2019-11-21"
    }
  ]
}